README
setup.py
test/test_sourcer.py
tiddlywebplugins/__init__.py
tiddlywebplugins.instancer.egg-info/PKG-INFO
tiddlywebplugins.instancer.egg-info/SOURCES.txt
tiddlywebplugins.instancer.egg-info/dependency_links.txt
tiddlywebplugins.instancer.egg-info/namespace_packages.txt
tiddlywebplugins.instancer.egg-info/not-zip-safe
tiddlywebplugins.instancer.egg-info/requires.txt
tiddlywebplugins.instancer.egg-info/top_level.txt
tiddlywebplugins/instancer/__init__.py
tiddlywebplugins/instancer/sourcer.py
tiddlywebplugins/instancer/util.py