Metadata-Version: 1.0
Name: tiddlywebplugins.instancer
Version: 0.7.16
Summary: utilities to simplify instance management for TiddlyWeb verticals
Home-page: http://pypi.python.org/pypi/tiddlywebplugins.instancer
Author: FND
Author-email: FNDo@gmx.net
License: UNKNOWN
Platform: Posix; MacOS X; Windows
